{
    "os": "Linux-5.4.0-174-generic-x86_64-with-glibc2.31",
    "python": "3.12.2",
    "heartbeatAt": "2024-05-15T17:26:45.797462",
    "startedAt": "2024-05-15T17:26:44.851613",
    "docker": null,
    "cuda": null,
    "args": [
        "--eps",
        "0.3",
        "--epochs",
        "200"
    ],
    "state": "running",
    "program": "/raid/ganesh/racha_suraj/SF_test/Power-Mechanism-new/Adult_income/test_income.py",
    "codePathLocal": "test_income.py",
    "codePath": "Adult_income/test_income.py",
    "git": {
        "remote": "https://github.com/Kaustubh-iitb/Power-Mechanism-new.git",
        "commit": "2ac359c7d10d049b728700bcce9c4954289f7734"
    },
    "email": "ponkshekaustubh11@gmail.com",
    "root": "/raid/ganesh/racha_suraj/SF_test/Power-Mechanism-new",
    "host": "iitb-dgx4.iitb.ac.in",
    "username": "racha_suraj",
    "executable": "/raid/ganesh/racha_suraj/miniconda3/envs/dpo/bin/python",
    "cpu_count": 128,
    "cpu_count_logical": 256,
    "cpu_freq": {
        "current": 3332.4860976562495,
        "min": 1500.0,
        "max": 2250.0
    },
    "cpu_freq_per_core": [
        {
            "current": 3389.759,
            "min": 1500.0,
            "max": 2250.0
        },
        {
            "current": 2226.827,
            "min": 1500.0,
            "max": 2250.0
        },
        {
            "current": 2239.06,
            "min": 1500.0,
            "max": 2250.0
        },
        {
            "current": 3256.255,
            "min": 1500.0,
            "max": 2250.0
        },
        {
            "current": 2553.615,
            "min": 1500.0,
            "max": 2250.0
        },
        {
            "current": 1735.544,
            "min": 1500.0,
            "max": 2250.0
        },
        {
            "current": 2542.336,
            "min": 1500.0,
            "max": 2250.0
        },
        {
            "current": 2508.919,
            "min": 1500.0,
            "max": 2250.0
        },
        {
            "current": 2113.298,
            "min": 1500.0,
            "max": 2250.0
        },
        {
            "current": 3069.22,
            "min": 1500.0,
            "max": 2250.0
        },
        {
            "current": 3052.028,
            "min": 1500.0,
            "max": 2250.0
        },
        {
            "current": 3243.184,
            "min": 1500.0,
            "max": 2250.0
        },
        {
            "current": 3381.809,
            "min": 1500.0,
            "max": 2250.0
        },
        {
            "current": 3302.333,
            "min": 1500.0,
            "max": 2250.0
        },
        {
            "current": 3388.696,
            "min": 1500.0,
            "max": 2250.0
        },
        {
            "current": 2397.856,
            "min": 1500.0,
            "max": 2250.0
        },
        {
            "current": 3385.156,
            "min": 1500.0,
            "max": 2250.0
        },
        {
            "current": 2523.347,
            "min": 1500.0,
            "max": 2250.0
        },
        {
            "current": 3395.277,
            "min": 1500.0,
            "max": 2250.0
        },
        {
            "current": 3391.234,
            "min": 1500.0,
            "max": 2250.0
        },
        {
            "current": 3390.277,
            "min": 1500.0,
            "max": 2250.0
        },
        {
            "current": 2890.604,
            "min": 1500.0,
            "max": 2250.0
        },
        {
            "current": 3389.772,
            "min": 1500.0,
            "max": 2250.0
        },
        {
            "current": 3400.448,
            "min": 1500.0,
            "max": 2250.0
        },
        {
            "current": 3386.925,
            "min": 1500.0,
            "max": 2250.0
        },
        {
            "current": 3369.323,
            "min": 1500.0,
            "max": 2250.0
        },
        {
            "current": 3389.449,
            "min": 1500.0,
            "max": 2250.0
        },
        {
            "current": 3414.649,
            "min": 1500.0,
            "max": 2250.0
        },
        {
            "current": 3387.627,
            "min": 1500.0,
            "max": 2250.0
        },
        {
            "current": 3384.665,
            "min": 1500.0,
            "max": 2250.0
        },
        {
            "current": 3366.236,
            "min": 1500.0,
            "max": 2250.0
        },
        {
            "current": 3389.993,
            "min": 1500.0,
            "max": 2250.0
        },
        {
            "current": 3390.136,
            "min": 1500.0,
            "max": 2250.0
        },
        {
            "current": 3391.29,
            "min": 1500.0,
            "max": 2250.0
        },
        {
            "current": 2264.344,
            "min": 1500.0,
            "max": 2250.0
        },
        {
            "current": 2225.309,
            "min": 1500.0,
            "max": 2250.0
        },
        {
            "current": 3386.368,
            "min": 1500.0,
            "max": 2250.0
        },
        {
            "current": 3197.489,
            "min": 1500.0,
            "max": 2250.0
        },
        {
            "current": 3404.04,
            "min": 1500.0,
            "max": 2250.0
        },
        {
            "current": 3386.568,
            "min": 1500.0,
            "max": 2250.0
        },
        {
            "current": 3382.714,
            "min": 1500.0,
            "max": 2250.0
        },
        {
            "current": 3388.4,
            "min": 1500.0,
            "max": 2250.0
        },
        {
            "current": 3399.303,
            "min": 1500.0,
            "max": 2250.0
        },
        {
            "current": 3389.518,
            "min": 1500.0,
            "max": 2250.0
        },
        {
            "current": 3389.342,
            "min": 1500.0,
            "max": 2250.0
        },
        {
            "current": 3375.721,
            "min": 1500.0,
            "max": 2250.0
        },
        {
            "current": 2198.779,
            "min": 1500.0,
            "max": 2250.0
        },
        {
            "current": 3393.064,
            "min": 1500.0,
            "max": 2250.0
        },
        {
            "current": 3392.615,
            "min": 1500.0,
            "max": 2250.0
        },
        {
            "current": 3369.599,
            "min": 1500.0,
            "max": 2250.0
        },
        {
            "current": 3403.977,
            "min": 1500.0,
            "max": 2250.0
        },
        {
            "current": 3382.708,
            "min": 1500.0,
            "max": 2250.0
        },
        {
            "current": 3374.953,
            "min": 1500.0,
            "max": 2250.0
        },
        {
            "current": 3395.992,
            "min": 1500.0,
            "max": 2250.0
        },
        {
            "current": 3399.115,
            "min": 1500.0,
            "max": 2250.0
        },
        {
            "current": 3384.566,
            "min": 1500.0,
            "max": 2250.0
        },
        {
            "current": 3383.409,
            "min": 1500.0,
            "max": 2250.0
        },
        {
            "current": 3389.521,
            "min": 1500.0,
            "max": 2250.0
        },
        {
            "current": 3391.875,
            "min": 1500.0,
            "max": 2250.0
        },
        {
            "current": 2164.179,
            "min": 1500.0,
            "max": 2250.0
        },
        {
            "current": 3392.411,
            "min": 1500.0,
            "max": 2250.0
        },
        {
            "current": 3393.197,
            "min": 1500.0,
            "max": 2250.0
        },
        {
            "current": 3391.022,
            "min": 1500.0,
            "max": 2250.0
        },
        {
            "current": 3388.499,
            "min": 1500.0,
            "max": 2250.0
        },
        {
            "current": 3394.359,
            "min": 1500.0,
            "max": 2250.0
        },
        {
            "current": 3138.699,
            "min": 1500.0,
            "max": 2250.0
        },
        {
            "current": 3382.355,
            "min": 1500.0,
            "max": 2250.0
        },
        {
            "current": 2166.238,
            "min": 1500.0,
            "max": 2250.0
        },
        {
            "current": 3392.233,
            "min": 1500.0,
            "max": 2250.0
        },
        {
            "current": 2226.521,
            "min": 1500.0,
            "max": 2250.0
        },
        {
            "current": 3381.179,
            "min": 1500.0,
            "max": 2250.0
        },
        {
            "current": 3384.856,
            "min": 1500.0,
            "max": 2250.0
        },
        {
            "current": 3397.724,
            "min": 1500.0,
            "max": 2250.0
        },
        {
            "current": 3381.517,
            "min": 1500.0,
            "max": 2250.0
        },
        {
            "current": 3385.243,
            "min": 1500.0,
            "max": 2250.0
        },
        {
            "current": 3384.07,
            "min": 1500.0,
            "max": 2250.0
        },
        {
            "current": 3385.224,
            "min": 1500.0,
            "max": 2250.0
        },
        {
            "current": 3386.751,
            "min": 1500.0,
            "max": 2250.0
        },
        {
            "current": 3389.103,
            "min": 1500.0,
            "max": 2250.0
        },
        {
            "current": 3396.809,
            "min": 1500.0,
            "max": 2250.0
        },
        {
            "current": 3393.601,
            "min": 1500.0,
            "max": 2250.0
        },
        {
            "current": 3380.501,
            "min": 1500.0,
            "max": 2250.0
        },
        {
            "current": 3389.054,
            "min": 1500.0,
            "max": 2250.0
        },
        {
            "current": 3390.491,
            "min": 1500.0,
            "max": 2250.0
        },
        {
            "current": 3387.934,
            "min": 1500.0,
            "max": 2250.0
        },
        {
            "current": 3386.495,
            "min": 1500.0,
            "max": 2250.0
        },
        {
            "current": 2253.113,
            "min": 1500.0,
            "max": 2250.0
        },
        {
            "current": 3398.432,
            "min": 1500.0,
            "max": 2250.0
        },
        {
            "current": 3392.355,
            "min": 1500.0,
            "max": 2250.0
        },
        {
            "current": 3391.902,
            "min": 1500.0,
            "max": 2250.0
        },
        {
            "current": 3388.019,
            "min": 1500.0,
            "max": 2250.0
        },
        {
            "current": 3380.283,
            "min": 1500.0,
            "max": 2250.0
        },
        {
            "current": 3391.959,
            "min": 1500.0,
            "max": 2250.0
        },
        {
            "current": 3392.359,
            "min": 1500.0,
            "max": 2250.0
        },
        {
            "current": 3395.243,
            "min": 1500.0,
            "max": 2250.0
        },
        {
            "current": 3390.701,
            "min": 1500.0,
            "max": 2250.0
        },
        {
            "current": 3387.659,
            "min": 1500.0,
            "max": 2250.0
        },
        {
            "current": 2340.708,
            "min": 1500.0,
            "max": 2250.0
        },
        {
            "current": 3379.246,
            "min": 1500.0,
            "max": 2250.0
        },
        {
            "current": 3401.735,
            "min": 1500.0,
            "max": 2250.0
        },
        {
            "current": 3387.808,
            "min": 1500.0,
            "max": 2250.0
        },
        {
            "current": 3396.752,
            "min": 1500.0,
            "max": 2250.0
        },
        {
            "current": 3388.305,
            "min": 1500.0,
            "max": 2250.0
        },
        {
            "current": 3374.8,
            "min": 1500.0,
            "max": 2250.0
        },
        {
            "current": 3381.83,
            "min": 1500.0,
            "max": 2250.0
        },
        {
            "current": 3386.179,
            "min": 1500.0,
            "max": 2250.0
        },
        {
            "current": 3387.214,
            "min": 1500.0,
            "max": 2250.0
        },
        {
            "current": 2543.8,
            "min": 1500.0,
            "max": 2250.0
        },
        {
            "current": 3397.039,
            "min": 1500.0,
            "max": 2250.0
        },
        {
            "current": 2466.152,
            "min": 1500.0,
            "max": 2250.0
        },
        {
            "current": 2267.92,
            "min": 1500.0,
            "max": 2250.0
        },
        {
            "current": 2154.495,
            "min": 1500.0,
            "max": 2250.0
        },
        {
            "current": 3390.33,
            "min": 1500.0,
            "max": 2250.0
        },
        {
            "current": 3391.629,
            "min": 1500.0,
            "max": 2250.0
        },
        {
            "current": 3401.492,
            "min": 1500.0,
            "max": 2250.0
        },
        {
            "current": 3392.436,
            "min": 1500.0,
            "max": 2250.0
        },
        {
            "current": 2298.067,
            "min": 1500.0,
            "max": 2250.0
        },
        {
            "current": 2238.307,
            "min": 1500.0,
            "max": 2250.0
        },
        {
            "current": 3397.026,
            "min": 1500.0,
            "max": 2250.0
        },
        {
            "current": 2268.794,
            "min": 1500.0,
            "max": 2250.0
        },
        {
            "current": 3385.938,
            "min": 1500.0,
            "max": 2250.0
        },
        {
            "current": 2243.623,
            "min": 1500.0,
            "max": 2250.0
        },
        {
            "current": 3388.091,
            "min": 1500.0,
            "max": 2250.0
        },
        {
            "current": 3399.921,
            "min": 1500.0,
            "max": 2250.0
        },
        {
            "current": 2526.936,
            "min": 1500.0,
            "max": 2250.0
        },
        {
            "current": 3390.718,
            "min": 1500.0,
            "max": 2250.0
        },
        {
            "current": 3386.688,
            "min": 1500.0,
            "max": 2250.0
        },
        {
            "current": 3388.023,
            "min": 1500.0,
            "max": 2250.0
        },
        {
            "current": 3395.569,
            "min": 1500.0,
            "max": 2250.0
        },
        {
            "current": 3395.601,
            "min": 1500.0,
            "max": 2250.0
        },
        {
            "current": 3390.442,
            "min": 1500.0,
            "max": 2250.0
        },
        {
            "current": 3378.384,
            "min": 1500.0,
            "max": 2250.0
        },
        {
            "current": 3403.526,
            "min": 1500.0,
            "max": 2250.0
        },
        {
            "current": 3390.327,
            "min": 1500.0,
            "max": 2250.0
        },
        {
            "current": 3391.271,
            "min": 1500.0,
            "max": 2250.0
        },
        {
            "current": 3388.993,
            "min": 1500.0,
            "max": 2250.0
        },
        {
            "current": 3402.071,
            "min": 1500.0,
            "max": 2250.0
        },
        {
            "current": 3395.244,
            "min": 1500.0,
            "max": 2250.0
        },
        {
            "current": 3382.34,
            "min": 1500.0,
            "max": 2250.0
        },
        {
            "current": 3380.736,
            "min": 1500.0,
            "max": 2250.0
        },
        {
            "current": 3393.167,
            "min": 1500.0,
            "max": 2250.0
        },
        {
            "current": 2374.005,
            "min": 1500.0,
            "max": 2250.0
        },
        {
            "current": 2333.142,
            "min": 1500.0,
            "max": 2250.0
        },
        {
            "current": 3378.684,
            "min": 1500.0,
            "max": 2250.0
        },
        {
            "current": 3373.259,
            "min": 1500.0,
            "max": 2250.0
        },
        {
            "current": 2501.209,
            "min": 1500.0,
            "max": 2250.0
        },
        {
            "current": 3392.299,
            "min": 1500.0,
            "max": 2250.0
        },
        {
            "current": 3380.403,
            "min": 1500.0,
            "max": 2250.0
        },
        {
            "current": 3378.688,
            "min": 1500.0,
            "max": 2250.0
        },
        {
            "current": 2798.399,
            "min": 1500.0,
            "max": 2250.0
        },
        {
            "current": 3387.803,
            "min": 1500.0,
            "max": 2250.0
        },
        {
            "current": 3400.693,
            "min": 1500.0,
            "max": 2250.0
        },
        {
            "current": 3385.498,
            "min": 1500.0,
            "max": 2250.0
        },
        {
            "current": 3387.905,
            "min": 1500.0,
            "max": 2250.0
        },
        {
            "current": 3385.0,
            "min": 1500.0,
            "max": 2250.0
        },
        {
            "current": 3390.772,
            "min": 1500.0,
            "max": 2250.0
        },
        {
            "current": 3370.972,
            "min": 1500.0,
            "max": 2250.0
        },
        {
            "current": 3398.61,
            "min": 1500.0,
            "max": 2250.0
        },
        {
            "current": 3376.199,
            "min": 1500.0,
            "max": 2250.0
        },
        {
            "current": 3375.032,
            "min": 1500.0,
            "max": 2250.0
        },
        {
            "current": 3376.553,
            "min": 1500.0,
            "max": 2250.0
        },
        {
            "current": 3391.387,
            "min": 1500.0,
            "max": 2250.0
        },
        {
            "current": 3388.681,
            "min": 1500.0,
            "max": 2250.0
        },
        {
            "current": 3399.29,
            "min": 1500.0,
            "max": 2250.0
        },
        {
            "current": 3389.397,
            "min": 1500.0,
            "max": 2250.0
        },
        {
            "current": 3396.644,
            "min": 1500.0,
            "max": 2250.0
        },
        {
            "current": 3386.462,
            "min": 1500.0,
            "max": 2250.0
        },
        {
            "current": 3389.959,
            "min": 1500.0,
            "max": 2250.0
        },
        {
            "current": 3379.618,
            "min": 1500.0,
            "max": 2250.0
        },
        {
            "current": 3379.447,
            "min": 1500.0,
            "max": 2250.0
        },
        {
            "current": 3397.307,
            "min": 1500.0,
            "max": 2250.0
        },
        {
            "current": 3392.034,
            "min": 1500.0,
            "max": 2250.0
        },
        {
            "current": 3390.488,
            "min": 1500.0,
            "max": 2250.0
        },
        {
            "current": 3399.373,
            "min": 1500.0,
            "max": 2250.0
        },
        {
            "current": 3395.693,
            "min": 1500.0,
            "max": 2250.0
        },
        {
            "current": 3391.001,
            "min": 1500.0,
            "max": 2250.0
        },
        {
            "current": 3377.107,
            "min": 1500.0,
            "max": 2250.0
        },
        {
            "current": 3388.769,
            "min": 1500.0,
            "max": 2250.0
        },
        {
            "current": 3393.129,
            "min": 1500.0,
            "max": 2250.0
        },
        {
            "current": 3403.319,
            "min": 1500.0,
            "max": 2250.0
        },
        {
            "current": 3385.909,
            "min": 1500.0,
            "max": 2250.0
        },
        {
            "current": 3383.727,
            "min": 1500.0,
            "max": 2250.0
        },
        {
            "current": 2201.303,
            "min": 1500.0,
            "max": 2250.0
        },
        {
            "current": 2240.535,
            "min": 1500.0,
            "max": 2250.0
        },
        {
            "current": 3375.649,
            "min": 1500.0,
            "max": 2250.0
        },
        {
            "current": 3387.912,
            "min": 1500.0,
            "max": 2250.0
        },
        {
            "current": 1704.904,
            "min": 1500.0,
            "max": 2250.0
        },
        {
            "current": 3392.125,
            "min": 1500.0,
            "max": 2250.0
        },
        {
            "current": 3381.679,
            "min": 1500.0,
            "max": 2250.0
        },
        {
            "current": 3391.909,
            "min": 1500.0,
            "max": 2250.0
        },
        {
            "current": 3398.63,
            "min": 1500.0,
            "max": 2250.0
        },
        {
            "current": 3379.005,
            "min": 1500.0,
            "max": 2250.0
        },
        {
            "current": 3390.881,
            "min": 1500.0,
            "max": 2250.0
        },
        {
            "current": 2244.828,
            "min": 1500.0,
            "max": 2250.0
        },
        {
            "current": 3394.902,
            "min": 1500.0,
            "max": 2250.0
        },
        {
            "current": 2194.847,
            "min": 1500.0,
            "max": 2250.0
        },
        {
            "current": 3384.681,
            "min": 1500.0,
            "max": 2250.0
        },
        {
            "current": 2715.576,
            "min": 1500.0,
            "max": 2250.0
        },
        {
            "current": 3391.84,
            "min": 1500.0,
            "max": 2250.0
        },
        {
            "current": 3384.254,
            "min": 1500.0,
            "max": 2250.0
        },
        {
            "current": 3394.593,
            "min": 1500.0,
            "max": 2250.0
        },
        {
            "current": 3376.819,
            "min": 1500.0,
            "max": 2250.0
        },
        {
            "current": 3400.387,
            "min": 1500.0,
            "max": 2250.0
        },
        {
            "current": 3391.948,
            "min": 1500.0,
            "max": 2250.0
        },
        {
            "current": 3383.854,
            "min": 1500.0,
            "max": 2250.0
        },
        {
            "current": 3380.981,
            "min": 1500.0,
            "max": 2250.0
        },
        {
            "current": 3390.945,
            "min": 1500.0,
            "max": 2250.0
        },
        {
            "current": 3391.505,
            "min": 1500.0,
            "max": 2250.0
        },
        {
            "current": 3387.543,
            "min": 1500.0,
            "max": 2250.0
        },
        {
            "current": 3390.398,
            "min": 1500.0,
            "max": 2250.0
        },
        {
            "current": 3374.984,
            "min": 1500.0,
            "max": 2250.0
        },
        {
            "current": 3385.285,
            "min": 1500.0,
            "max": 2250.0
        },
        {
            "current": 3391.882,
            "min": 1500.0,
            "max": 2250.0
        },
        {
            "current": 3396.844,
            "min": 1500.0,
            "max": 2250.0
        },
        {
            "current": 2228.186,
            "min": 1500.0,
            "max": 2250.0
        },
        {
            "current": 3399.828,
            "min": 1500.0,
            "max": 2250.0
        },
        {
            "current": 3392.01,
            "min": 1500.0,
            "max": 2250.0
        },
        {
            "current": 3392.386,
            "min": 1500.0,
            "max": 2250.0
        },
        {
            "current": 3376.34,
            "min": 1500.0,
            "max": 2250.0
        },
        {
            "current": 3391.381,
            "min": 1500.0,
            "max": 2250.0
        },
        {
            "current": 3391.117,
            "min": 1500.0,
            "max": 2250.0
        },
        {
            "current": 3391.399,
            "min": 1500.0,
            "max": 2250.0
        },
        {
            "current": 3391.049,
            "min": 1500.0,
            "max": 2250.0
        },
        {
            "current": 3392.813,
            "min": 1500.0,
            "max": 2250.0
        },
        {
            "current": 3399.29,
            "min": 1500.0,
            "max": 2250.0
        },
        {
            "current": 3259.733,
            "min": 1500.0,
            "max": 2250.0
        },
        {
            "current": 3395.894,
            "min": 1500.0,
            "max": 2250.0
        },
        {
            "current": 3390.923,
            "min": 1500.0,
            "max": 2250.0
        },
        {
            "current": 3375.363,
            "min": 1500.0,
            "max": 2250.0
        },
        {
            "current": 3382.189,
            "min": 1500.0,
            "max": 2250.0
        },
        {
            "current": 3385.022,
            "min": 1500.0,
            "max": 2250.0
        },
        {
            "current": 3384.058,
            "min": 1500.0,
            "max": 2250.0
        },
        {
            "current": 3389.209,
            "min": 1500.0,
            "max": 2250.0
        },
        {
            "current": 3394.623,
            "min": 1500.0,
            "max": 2250.0
        },
        {
            "current": 3389.231,
            "min": 1500.0,
            "max": 2250.0
        },
        {
            "current": 2599.924,
            "min": 1500.0,
            "max": 2250.0
        },
        {
            "current": 3390.346,
            "min": 1500.0,
            "max": 2250.0
        },
        {
            "current": 2692.366,
            "min": 1500.0,
            "max": 2250.0
        },
        {
            "current": 2230.65,
            "min": 1500.0,
            "max": 2250.0
        },
        {
            "current": 2225.434,
            "min": 1500.0,
            "max": 2250.0
        },
        {
            "current": 3399.681,
            "min": 1500.0,
            "max": 2250.0
        },
        {
            "current": 3380.416,
            "min": 1500.0,
            "max": 2250.0
        },
        {
            "current": 3391.529,
            "min": 1500.0,
            "max": 2250.0
        },
        {
            "current": 3393.187,
            "min": 1500.0,
            "max": 2250.0
        },
        {
            "current": 2070.943,
            "min": 1500.0,
            "max": 2250.0
        },
        {
            "current": 2039.865,
            "min": 1500.0,
            "max": 2250.0
        },
        {
            "current": 3022.412,
            "min": 1500.0,
            "max": 2250.0
        },
        {
            "current": 2215.27,
            "min": 1500.0,
            "max": 2250.0
        },
        {
            "current": 2406.58,
            "min": 1500.0,
            "max": 2250.0
        },
        {
            "current": 1605.112,
            "min": 1500.0,
            "max": 2250.0
        },
        {
            "current": 3184.616,
            "min": 1500.0,
            "max": 2250.0
        },
        {
            "current": 2559.618,
            "min": 1500.0,
            "max": 2250.0
        },
        {
            "current": 2547.664,
            "min": 1500.0,
            "max": 2250.0
        },
        {
            "current": 3387.762,
            "min": 1500.0,
            "max": 2250.0
        },
        {
            "current": 3394.418,
            "min": 1500.0,
            "max": 2250.0
        },
        {
            "current": 3392.071,
            "min": 1500.0,
            "max": 2250.0
        }
    ],
    "disk": {
        "/": {
            "total": 1757.7545127868652,
            "used": 1271.0740089416504
        }
    },
    "gpu": "NVIDIA A100-SXM4-80GB",
    "gpu_count": 8,
    "gpu_devices": [
        {
            "name": "NVIDIA A100-SXM4-80GB",
            "memory_total": 85899345920
        },
        {
            "name": "NVIDIA A100-SXM4-80GB",
            "memory_total": 85899345920
        },
        {
            "name": "NVIDIA A100-SXM4-80GB",
            "memory_total": 85899345920
        },
        {
            "name": "NVIDIA A100-SXM4-80GB",
            "memory_total": 85899345920
        },
        {
            "name": "NVIDIA A100-SXM4-80GB",
            "memory_total": 85899345920
        },
        {
            "name": "NVIDIA A100-SXM4-80GB",
            "memory_total": 85899345920
        },
        {
            "name": "NVIDIA A100-SXM4-80GB",
            "memory_total": 85899345920
        },
        {
            "name": "NVIDIA A100-SXM4-80GB",
            "memory_total": 85899345920
        }
    ],
    "memory": {
        "total": 2015.6736488342285
    }
}
