{
    "os": "Linux-5.4.0-174-generic-x86_64-with-glibc2.31",
    "python": "3.12.2",
    "heartbeatAt": "2024-05-13T13:01:23.568025",
    "startedAt": "2024-05-13T13:01:22.464841",
    "docker": null,
    "cuda": null,
    "args": [
        "--batch_size",
        "512",
        "--max_steps",
        "50"
    ],
    "state": "running",
    "program": "/raid/ganesh/racha_suraj/SF_test/Power-Mechanism-new/Higgs/higgs_train.py",
    "codePathLocal": "higgs_train.py",
    "codePath": "Higgs/higgs_train.py",
    "git": {
        "remote": "https://github.com/Kaustubh-iitb/Power-Mechanism-new.git",
        "commit": "2ac359c7d10d049b728700bcce9c4954289f7734"
    },
    "email": "ponkshekaustubh11@gmail.com",
    "root": "/raid/ganesh/racha_suraj/SF_test/Power-Mechanism-new",
    "host": "iitb-dgx4.iitb.ac.in",
    "username": "racha_suraj",
    "executable": "/raid/ganesh/racha_suraj/miniconda3/envs/dpo/bin/python",
    "cpu_count": 128,
    "cpu_count_logical": 256,
    "cpu_freq": {
        "current": 3044.987519531252,
        "min": 1500.0,
        "max": 2250.0
    },
    "cpu_freq_per_core": [
        {
            "current": 3388.594,
            "min": 1500.0,
            "max": 2250.0
        },
        {
            "current": 1689.905,
            "min": 1500.0,
            "max": 2250.0
        },
        {
            "current": 2226.78,
            "min": 1500.0,
            "max": 2250.0
        },
        {
            "current": 3374.902,
            "min": 1500.0,
            "max": 2250.0
        },
        {
            "current": 3397.042,
            "min": 1500.0,
            "max": 2250.0
        },
        {
            "current": 3375.512,
            "min": 1500.0,
            "max": 2250.0
        },
        {
            "current": 3398.932,
            "min": 1500.0,
            "max": 2250.0
        },
        {
            "current": 2220.907,
            "min": 1500.0,
            "max": 2250.0
        },
        {
            "current": 3392.95,
            "min": 1500.0,
            "max": 2250.0
        },
        {
            "current": 3385.896,
            "min": 1500.0,
            "max": 2250.0
        },
        {
            "current": 1815.252,
            "min": 1500.0,
            "max": 2250.0
        },
        {
            "current": 3395.277,
            "min": 1500.0,
            "max": 2250.0
        },
        {
            "current": 3387.006,
            "min": 1500.0,
            "max": 2250.0
        },
        {
            "current": 3344.826,
            "min": 1500.0,
            "max": 2250.0
        },
        {
            "current": 3388.985,
            "min": 1500.0,
            "max": 2250.0
        },
        {
            "current": 3388.585,
            "min": 1500.0,
            "max": 2250.0
        },
        {
            "current": 2562.286,
            "min": 1500.0,
            "max": 2250.0
        },
        {
            "current": 2534.588,
            "min": 1500.0,
            "max": 2250.0
        },
        {
            "current": 2550.496,
            "min": 1500.0,
            "max": 2250.0
        },
        {
            "current": 3383.045,
            "min": 1500.0,
            "max": 2250.0
        },
        {
            "current": 3380.112,
            "min": 1500.0,
            "max": 2250.0
        },
        {
            "current": 3391.725,
            "min": 1500.0,
            "max": 2250.0
        },
        {
            "current": 3392.154,
            "min": 1500.0,
            "max": 2250.0
        },
        {
            "current": 3397.614,
            "min": 1500.0,
            "max": 2250.0
        },
        {
            "current": 3390.375,
            "min": 1500.0,
            "max": 2250.0
        },
        {
            "current": 3389.105,
            "min": 1500.0,
            "max": 2250.0
        },
        {
            "current": 3391.644,
            "min": 1500.0,
            "max": 2250.0
        },
        {
            "current": 3391.113,
            "min": 1500.0,
            "max": 2250.0
        },
        {
            "current": 3384.68,
            "min": 1500.0,
            "max": 2250.0
        },
        {
            "current": 3398.404,
            "min": 1500.0,
            "max": 2250.0
        },
        {
            "current": 2564.368,
            "min": 1500.0,
            "max": 2250.0
        },
        {
            "current": 2265.862,
            "min": 1500.0,
            "max": 2250.0
        },
        {
            "current": 3393.331,
            "min": 1500.0,
            "max": 2250.0
        },
        {
            "current": 3389.562,
            "min": 1500.0,
            "max": 2250.0
        },
        {
            "current": 3368.253,
            "min": 1500.0,
            "max": 2250.0
        },
        {
            "current": 3391.273,
            "min": 1500.0,
            "max": 2250.0
        },
        {
            "current": 3387.707,
            "min": 1500.0,
            "max": 2250.0
        },
        {
            "current": 3375.745,
            "min": 1500.0,
            "max": 2250.0
        },
        {
            "current": 3391.093,
            "min": 1500.0,
            "max": 2250.0
        },
        {
            "current": 3390.696,
            "min": 1500.0,
            "max": 2250.0
        },
        {
            "current": 3242.171,
            "min": 1500.0,
            "max": 2250.0
        },
        {
            "current": 3240.967,
            "min": 1500.0,
            "max": 2250.0
        },
        {
            "current": 3225.267,
            "min": 1500.0,
            "max": 2250.0
        },
        {
            "current": 3233.903,
            "min": 1500.0,
            "max": 2250.0
        },
        {
            "current": 3365.459,
            "min": 1500.0,
            "max": 2250.0
        },
        {
            "current": 3391.408,
            "min": 1500.0,
            "max": 2250.0
        },
        {
            "current": 3391.605,
            "min": 1500.0,
            "max": 2250.0
        },
        {
            "current": 3380.889,
            "min": 1500.0,
            "max": 2250.0
        },
        {
            "current": 3383.913,
            "min": 1500.0,
            "max": 2250.0
        },
        {
            "current": 3401.307,
            "min": 1500.0,
            "max": 2250.0
        },
        {
            "current": 2561.408,
            "min": 1500.0,
            "max": 2250.0
        },
        {
            "current": 1697.07,
            "min": 1500.0,
            "max": 2250.0
        },
        {
            "current": 3383.067,
            "min": 1500.0,
            "max": 2250.0
        },
        {
            "current": 2573.568,
            "min": 1500.0,
            "max": 2250.0
        },
        {
            "current": 2232.906,
            "min": 1500.0,
            "max": 2250.0
        },
        {
            "current": 2185.983,
            "min": 1500.0,
            "max": 2250.0
        },
        {
            "current": 3379.941,
            "min": 1500.0,
            "max": 2250.0
        },
        {
            "current": 3387.534,
            "min": 1500.0,
            "max": 2250.0
        },
        {
            "current": 3409.257,
            "min": 1500.0,
            "max": 2250.0
        },
        {
            "current": 2183.416,
            "min": 1500.0,
            "max": 2250.0
        },
        {
            "current": 2178.389,
            "min": 1500.0,
            "max": 2250.0
        },
        {
            "current": 2796.885,
            "min": 1500.0,
            "max": 2250.0
        },
        {
            "current": 2279.332,
            "min": 1500.0,
            "max": 2250.0
        },
        {
            "current": 1867.123,
            "min": 1500.0,
            "max": 2250.0
        },
        {
            "current": 2213.82,
            "min": 1500.0,
            "max": 2250.0
        },
        {
            "current": 3384.52,
            "min": 1500.0,
            "max": 2250.0
        },
        {
            "current": 3393.049,
            "min": 1500.0,
            "max": 2250.0
        },
        {
            "current": 2181.242,
            "min": 1500.0,
            "max": 2250.0
        },
        {
            "current": 2291.093,
            "min": 1500.0,
            "max": 2250.0
        },
        {
            "current": 2296.756,
            "min": 1500.0,
            "max": 2250.0
        },
        {
            "current": 2240.14,
            "min": 1500.0,
            "max": 2250.0
        },
        {
            "current": 2298.73,
            "min": 1500.0,
            "max": 2250.0
        },
        {
            "current": 2275.277,
            "min": 1500.0,
            "max": 2250.0
        },
        {
            "current": 2285.952,
            "min": 1500.0,
            "max": 2250.0
        },
        {
            "current": 2258.942,
            "min": 1500.0,
            "max": 2250.0
        },
        {
            "current": 2270.139,
            "min": 1500.0,
            "max": 2250.0
        },
        {
            "current": 1755.183,
            "min": 1500.0,
            "max": 2250.0
        },
        {
            "current": 2293.058,
            "min": 1500.0,
            "max": 2250.0
        },
        {
            "current": 1752.817,
            "min": 1500.0,
            "max": 2250.0
        },
        {
            "current": 2286.834,
            "min": 1500.0,
            "max": 2250.0
        },
        {
            "current": 2626.617,
            "min": 1500.0,
            "max": 2250.0
        },
        {
            "current": 2322.245,
            "min": 1500.0,
            "max": 2250.0
        },
        {
            "current": 3305.516,
            "min": 1500.0,
            "max": 2250.0
        },
        {
            "current": 3395.811,
            "min": 1500.0,
            "max": 2250.0
        },
        {
            "current": 3384.729,
            "min": 1500.0,
            "max": 2250.0
        },
        {
            "current": 2533.017,
            "min": 1500.0,
            "max": 2250.0
        },
        {
            "current": 2547.252,
            "min": 1500.0,
            "max": 2250.0
        },
        {
            "current": 3380.522,
            "min": 1500.0,
            "max": 2250.0
        },
        {
            "current": 2257.999,
            "min": 1500.0,
            "max": 2250.0
        },
        {
            "current": 3388.133,
            "min": 1500.0,
            "max": 2250.0
        },
        {
            "current": 2226.287,
            "min": 1500.0,
            "max": 2250.0
        },
        {
            "current": 2162.776,
            "min": 1500.0,
            "max": 2250.0
        },
        {
            "current": 2450.175,
            "min": 1500.0,
            "max": 2250.0
        },
        {
            "current": 3397.259,
            "min": 1500.0,
            "max": 2250.0
        },
        {
            "current": 3391.978,
            "min": 1500.0,
            "max": 2250.0
        },
        {
            "current": 3352.777,
            "min": 1500.0,
            "max": 2250.0
        },
        {
            "current": 3389.093,
            "min": 1500.0,
            "max": 2250.0
        },
        {
            "current": 2164.502,
            "min": 1500.0,
            "max": 2250.0
        },
        {
            "current": 2171.794,
            "min": 1500.0,
            "max": 2250.0
        },
        {
            "current": 3392.112,
            "min": 1500.0,
            "max": 2250.0
        },
        {
            "current": 3383.35,
            "min": 1500.0,
            "max": 2250.0
        },
        {
            "current": 3294.302,
            "min": 1500.0,
            "max": 2250.0
        },
        {
            "current": 3386.17,
            "min": 1500.0,
            "max": 2250.0
        },
        {
            "current": 3377.258,
            "min": 1500.0,
            "max": 2250.0
        },
        {
            "current": 3392.333,
            "min": 1500.0,
            "max": 2250.0
        },
        {
            "current": 3385.02,
            "min": 1500.0,
            "max": 2250.0
        },
        {
            "current": 3395.097,
            "min": 1500.0,
            "max": 2250.0
        },
        {
            "current": 3406.676,
            "min": 1500.0,
            "max": 2250.0
        },
        {
            "current": 2559.189,
            "min": 1500.0,
            "max": 2250.0
        },
        {
            "current": 3373.904,
            "min": 1500.0,
            "max": 2250.0
        },
        {
            "current": 3369.836,
            "min": 1500.0,
            "max": 2250.0
        },
        {
            "current": 3394.086,
            "min": 1500.0,
            "max": 2250.0
        },
        {
            "current": 2567.024,
            "min": 1500.0,
            "max": 2250.0
        },
        {
            "current": 2524.986,
            "min": 1500.0,
            "max": 2250.0
        },
        {
            "current": 2453.214,
            "min": 1500.0,
            "max": 2250.0
        },
        {
            "current": 3362.916,
            "min": 1500.0,
            "max": 2250.0
        },
        {
            "current": 3379.446,
            "min": 1500.0,
            "max": 2250.0
        },
        {
            "current": 2473.002,
            "min": 1500.0,
            "max": 2250.0
        },
        {
            "current": 2502.654,
            "min": 1500.0,
            "max": 2250.0
        },
        {
            "current": 3387.556,
            "min": 1500.0,
            "max": 2250.0
        },
        {
            "current": 2544.611,
            "min": 1500.0,
            "max": 2250.0
        },
        {
            "current": 3400.944,
            "min": 1500.0,
            "max": 2250.0
        },
        {
            "current": 3392.596,
            "min": 1500.0,
            "max": 2250.0
        },
        {
            "current": 3392.412,
            "min": 1500.0,
            "max": 2250.0
        },
        {
            "current": 3308.735,
            "min": 1500.0,
            "max": 2250.0
        },
        {
            "current": 2432.389,
            "min": 1500.0,
            "max": 2250.0
        },
        {
            "current": 3393.642,
            "min": 1500.0,
            "max": 2250.0
        },
        {
            "current": 3378.502,
            "min": 1500.0,
            "max": 2250.0
        },
        {
            "current": 3385.244,
            "min": 1500.0,
            "max": 2250.0
        },
        {
            "current": 1694.904,
            "min": 1500.0,
            "max": 2250.0
        },
        {
            "current": 2184.036,
            "min": 1500.0,
            "max": 2250.0
        },
        {
            "current": 3392.423,
            "min": 1500.0,
            "max": 2250.0
        },
        {
            "current": 2949.765,
            "min": 1500.0,
            "max": 2250.0
        },
        {
            "current": 3391.264,
            "min": 1500.0,
            "max": 2250.0
        },
        {
            "current": 3396.811,
            "min": 1500.0,
            "max": 2250.0
        },
        {
            "current": 2171.001,
            "min": 1500.0,
            "max": 2250.0
        },
        {
            "current": 3404.002,
            "min": 1500.0,
            "max": 2250.0
        },
        {
            "current": 3406.556,
            "min": 1500.0,
            "max": 2250.0
        },
        {
            "current": 1813.935,
            "min": 1500.0,
            "max": 2250.0
        },
        {
            "current": 3378.623,
            "min": 1500.0,
            "max": 2250.0
        },
        {
            "current": 3386.398,
            "min": 1500.0,
            "max": 2250.0
        },
        {
            "current": 3375.531,
            "min": 1500.0,
            "max": 2250.0
        },
        {
            "current": 3393.996,
            "min": 1500.0,
            "max": 2250.0
        },
        {
            "current": 3387.669,
            "min": 1500.0,
            "max": 2250.0
        },
        {
            "current": 2489.966,
            "min": 1500.0,
            "max": 2250.0
        },
        {
            "current": 2560.077,
            "min": 1500.0,
            "max": 2250.0
        },
        {
            "current": 2569.311,
            "min": 1500.0,
            "max": 2250.0
        },
        {
            "current": 3390.786,
            "min": 1500.0,
            "max": 2250.0
        },
        {
            "current": 3389.447,
            "min": 1500.0,
            "max": 2250.0
        },
        {
            "current": 3337.92,
            "min": 1500.0,
            "max": 2250.0
        },
        {
            "current": 3382.915,
            "min": 1500.0,
            "max": 2250.0
        },
        {
            "current": 3409.565,
            "min": 1500.0,
            "max": 2250.0
        },
        {
            "current": 3389.93,
            "min": 1500.0,
            "max": 2250.0
        },
        {
            "current": 3391.03,
            "min": 1500.0,
            "max": 2250.0
        },
        {
            "current": 3391.686,
            "min": 1500.0,
            "max": 2250.0
        },
        {
            "current": 3400.156,
            "min": 1500.0,
            "max": 2250.0
        },
        {
            "current": 3099.073,
            "min": 1500.0,
            "max": 2250.0
        },
        {
            "current": 3102.255,
            "min": 1500.0,
            "max": 2250.0
        },
        {
            "current": 3104.507,
            "min": 1500.0,
            "max": 2250.0
        },
        {
            "current": 1692.837,
            "min": 1500.0,
            "max": 2250.0
        },
        {
            "current": 3391.33,
            "min": 1500.0,
            "max": 2250.0
        },
        {
            "current": 3390.071,
            "min": 1500.0,
            "max": 2250.0
        },
        {
            "current": 3390.847,
            "min": 1500.0,
            "max": 2250.0
        },
        {
            "current": 3391.125,
            "min": 1500.0,
            "max": 2250.0
        },
        {
            "current": 3390.905,
            "min": 1500.0,
            "max": 2250.0
        },
        {
            "current": 3389.61,
            "min": 1500.0,
            "max": 2250.0
        },
        {
            "current": 3388.281,
            "min": 1500.0,
            "max": 2250.0
        },
        {
            "current": 3388.524,
            "min": 1500.0,
            "max": 2250.0
        },
        {
            "current": 3237.125,
            "min": 1500.0,
            "max": 2250.0
        },
        {
            "current": 3239.445,
            "min": 1500.0,
            "max": 2250.0
        },
        {
            "current": 3236.158,
            "min": 1500.0,
            "max": 2250.0
        },
        {
            "current": 3234.439,
            "min": 1500.0,
            "max": 2250.0
        },
        {
            "current": 3374.379,
            "min": 1500.0,
            "max": 2250.0
        },
        {
            "current": 3394.215,
            "min": 1500.0,
            "max": 2250.0
        },
        {
            "current": 3399.931,
            "min": 1500.0,
            "max": 2250.0
        },
        {
            "current": 3391.29,
            "min": 1500.0,
            "max": 2250.0
        },
        {
            "current": 3383.13,
            "min": 1500.0,
            "max": 2250.0
        },
        {
            "current": 3378.237,
            "min": 1500.0,
            "max": 2250.0
        },
        {
            "current": 3399.393,
            "min": 1500.0,
            "max": 2250.0
        },
        {
            "current": 2183.759,
            "min": 1500.0,
            "max": 2250.0
        },
        {
            "current": 3391.722,
            "min": 1500.0,
            "max": 2250.0
        },
        {
            "current": 3409.708,
            "min": 1500.0,
            "max": 2250.0
        },
        {
            "current": 2194.053,
            "min": 1500.0,
            "max": 2250.0
        },
        {
            "current": 2183.119,
            "min": 1500.0,
            "max": 2250.0
        },
        {
            "current": 3390.573,
            "min": 1500.0,
            "max": 2250.0
        },
        {
            "current": 3393.895,
            "min": 1500.0,
            "max": 2250.0
        },
        {
            "current": 3406.307,
            "min": 1500.0,
            "max": 2250.0
        },
        {
            "current": 2200.042,
            "min": 1500.0,
            "max": 2250.0
        },
        {
            "current": 1694.602,
            "min": 1500.0,
            "max": 2250.0
        },
        {
            "current": 2538.616,
            "min": 1500.0,
            "max": 2250.0
        },
        {
            "current": 1691.834,
            "min": 1500.0,
            "max": 2250.0
        },
        {
            "current": 3369.172,
            "min": 1500.0,
            "max": 2250.0
        },
        {
            "current": 3392.154,
            "min": 1500.0,
            "max": 2250.0
        },
        {
            "current": 2180.01,
            "min": 1500.0,
            "max": 2250.0
        },
        {
            "current": 2182.891,
            "min": 1500.0,
            "max": 2250.0
        },
        {
            "current": 3394.92,
            "min": 1500.0,
            "max": 2250.0
        },
        {
            "current": 3386.843,
            "min": 1500.0,
            "max": 2250.0
        },
        {
            "current": 3391.758,
            "min": 1500.0,
            "max": 2250.0
        },
        {
            "current": 3393.438,
            "min": 1500.0,
            "max": 2250.0
        },
        {
            "current": 3390.454,
            "min": 1500.0,
            "max": 2250.0
        },
        {
            "current": 3395.721,
            "min": 1500.0,
            "max": 2250.0
        },
        {
            "current": 3402.792,
            "min": 1500.0,
            "max": 2250.0
        },
        {
            "current": 3395.055,
            "min": 1500.0,
            "max": 2250.0
        },
        {
            "current": 3397.839,
            "min": 1500.0,
            "max": 2250.0
        },
        {
            "current": 2503.55,
            "min": 1500.0,
            "max": 2250.0
        },
        {
            "current": 3406.291,
            "min": 1500.0,
            "max": 2250.0
        },
        {
            "current": 2481.326,
            "min": 1500.0,
            "max": 2250.0
        },
        {
            "current": 3387.965,
            "min": 1500.0,
            "max": 2250.0
        },
        {
            "current": 1687.252,
            "min": 1500.0,
            "max": 2250.0
        },
        {
            "current": 3400.164,
            "min": 1500.0,
            "max": 2250.0
        },
        {
            "current": 1692.727,
            "min": 1500.0,
            "max": 2250.0
        },
        {
            "current": 3399.581,
            "min": 1500.0,
            "max": 2250.0
        },
        {
            "current": 3379.6,
            "min": 1500.0,
            "max": 2250.0
        },
        {
            "current": 1692.527,
            "min": 1500.0,
            "max": 2250.0
        },
        {
            "current": 1698.897,
            "min": 1500.0,
            "max": 2250.0
        },
        {
            "current": 3377.308,
            "min": 1500.0,
            "max": 2250.0
        },
        {
            "current": 3375.891,
            "min": 1500.0,
            "max": 2250.0
        },
        {
            "current": 2209.617,
            "min": 1500.0,
            "max": 2250.0
        },
        {
            "current": 3371.435,
            "min": 1500.0,
            "max": 2250.0
        },
        {
            "current": 3388.329,
            "min": 1500.0,
            "max": 2250.0
        },
        {
            "current": 2478.714,
            "min": 1500.0,
            "max": 2250.0
        },
        {
            "current": 2171.657,
            "min": 1500.0,
            "max": 2250.0
        },
        {
            "current": 2209.797,
            "min": 1500.0,
            "max": 2250.0
        },
        {
            "current": 3201.924,
            "min": 1500.0,
            "max": 2250.0
        },
        {
            "current": 2203.255,
            "min": 1500.0,
            "max": 2250.0
        },
        {
            "current": 3375.702,
            "min": 1500.0,
            "max": 2250.0
        },
        {
            "current": 3384.936,
            "min": 1500.0,
            "max": 2250.0
        },
        {
            "current": 2183.012,
            "min": 1500.0,
            "max": 2250.0
        },
        {
            "current": 2284.318,
            "min": 1500.0,
            "max": 2250.0
        },
        {
            "current": 1756.917,
            "min": 1500.0,
            "max": 2250.0
        },
        {
            "current": 2259.108,
            "min": 1500.0,
            "max": 2250.0
        },
        {
            "current": 2270.543,
            "min": 1500.0,
            "max": 2250.0
        },
        {
            "current": 3402.682,
            "min": 1500.0,
            "max": 2250.0
        },
        {
            "current": 2178.412,
            "min": 1500.0,
            "max": 2250.0
        },
        {
            "current": 2195.555,
            "min": 1500.0,
            "max": 2250.0
        },
        {
            "current": 2197.038,
            "min": 1500.0,
            "max": 2250.0
        },
        {
            "current": 1695.337,
            "min": 1500.0,
            "max": 2250.0
        },
        {
            "current": 2182.385,
            "min": 1500.0,
            "max": 2250.0
        },
        {
            "current": 2205.642,
            "min": 1500.0,
            "max": 2250.0
        },
        {
            "current": 3385.006,
            "min": 1500.0,
            "max": 2250.0
        },
        {
            "current": 1690.958,
            "min": 1500.0,
            "max": 2250.0
        },
        {
            "current": 2563.656,
            "min": 1500.0,
            "max": 2250.0
        },
        {
            "current": 1691.55,
            "min": 1500.0,
            "max": 2250.0
        },
        {
            "current": 3391.888,
            "min": 1500.0,
            "max": 2250.0
        },
        {
            "current": 3382.605,
            "min": 1500.0,
            "max": 2250.0
        },
        {
            "current": 2776.173,
            "min": 1500.0,
            "max": 2250.0
        },
        {
            "current": 3300.183,
            "min": 1500.0,
            "max": 2250.0
        },
        {
            "current": 3389.735,
            "min": 1500.0,
            "max": 2250.0
        },
        {
            "current": 2444.132,
            "min": 1500.0,
            "max": 2250.0
        },
        {
            "current": 3374.188,
            "min": 1500.0,
            "max": 2250.0
        },
        {
            "current": 3383.812,
            "min": 1500.0,
            "max": 2250.0
        },
        {
            "current": 3393.951,
            "min": 1500.0,
            "max": 2250.0
        },
        {
            "current": 3332.252,
            "min": 1500.0,
            "max": 2250.0
        },
        {
            "current": 1700.634,
            "min": 1500.0,
            "max": 2250.0
        },
        {
            "current": 3388.387,
            "min": 1500.0,
            "max": 2250.0
        },
        {
            "current": 2228.244,
            "min": 1500.0,
            "max": 2250.0
        }
    ],
    "disk": {
        "/": {
            "total": 1757.7545127868652,
            "used": 1270.1541900634766
        }
    },
    "gpu": "NVIDIA A100-SXM4-80GB",
    "gpu_count": 8,
    "gpu_devices": [
        {
            "name": "NVIDIA A100-SXM4-80GB",
            "memory_total": 85899345920
        },
        {
            "name": "NVIDIA A100-SXM4-80GB",
            "memory_total": 85899345920
        },
        {
            "name": "NVIDIA A100-SXM4-80GB",
            "memory_total": 85899345920
        },
        {
            "name": "NVIDIA A100-SXM4-80GB",
            "memory_total": 85899345920
        },
        {
            "name": "NVIDIA A100-SXM4-80GB",
            "memory_total": 85899345920
        },
        {
            "name": "NVIDIA A100-SXM4-80GB",
            "memory_total": 85899345920
        },
        {
            "name": "NVIDIA A100-SXM4-80GB",
            "memory_total": 85899345920
        },
        {
            "name": "NVIDIA A100-SXM4-80GB",
            "memory_total": 85899345920
        }
    ],
    "memory": {
        "total": 2015.6736488342285
    }
}
