{
    "os": "Linux-5.4.0-174-generic-x86_64-with-glibc2.31",
    "python": "3.12.2",
    "heartbeatAt": "2024-05-19T15:00:25.799541",
    "startedAt": "2024-05-19T15:00:24.736251",
    "docker": null,
    "cuda": null,
    "args": [
        "--max_steps",
        "15000",
        "--epochs",
        "300",
        "--lr",
        "0.001",
        "--eps",
        "1.2",
        "--seed",
        "58"
    ],
    "state": "running",
    "program": "/raid/ganesh/racha_suraj/SF_test/Power-Mechanism-new/Higgs/priv_higgs_base.py",
    "codePathLocal": "priv_higgs_base.py",
    "codePath": "Higgs/priv_higgs_base.py",
    "git": {
        "remote": "https://github.com/Kaustubh-iitb/Power-Mechanism-new.git",
        "commit": "d0ed1f305d7d11cfb1a43d86afe9c7957faa19d9"
    },
    "email": "ponkshekaustubh11@gmail.com",
    "root": "/raid/ganesh/racha_suraj/SF_test/Power-Mechanism-new",
    "host": "iitb-dgx4.iitb.ac.in",
    "username": "racha_suraj",
    "executable": "/raid/ganesh/racha_suraj/miniconda3/envs/dpo/bin/python",
    "cpu_count": 128,
    "cpu_count_logical": 256,
    "cpu_freq": {
        "current": 3319.471218750001,
        "min": 1500.0,
        "max": 2250.0
    },
    "cpu_freq_per_core": [
        {
            "current": 3390.917,
            "min": 1500.0,
            "max": 2250.0
        },
        {
            "current": 3391.506,
            "min": 1500.0,
            "max": 2250.0
        },
        {
            "current": 3393.211,
            "min": 1500.0,
            "max": 2250.0
        },
        {
            "current": 3392.599,
            "min": 1500.0,
            "max": 2250.0
        },
        {
            "current": 3394.011,
            "min": 1500.0,
            "max": 2250.0
        },
        {
            "current": 3390.498,
            "min": 1500.0,
            "max": 2250.0
        },
        {
            "current": 3382.288,
            "min": 1500.0,
            "max": 2250.0
        },
        {
            "current": 2473.7,
            "min": 1500.0,
            "max": 2250.0
        },
        {
            "current": 2501.175,
            "min": 1500.0,
            "max": 2250.0
        },
        {
            "current": 2267.542,
            "min": 1500.0,
            "max": 2250.0
        },
        {
            "current": 2472.196,
            "min": 1500.0,
            "max": 2250.0
        },
        {
            "current": 2521.413,
            "min": 1500.0,
            "max": 2250.0
        },
        {
            "current": 3386.344,
            "min": 1500.0,
            "max": 2250.0
        },
        {
            "current": 3398.996,
            "min": 1500.0,
            "max": 2250.0
        },
        {
            "current": 3387.855,
            "min": 1500.0,
            "max": 2250.0
        },
        {
            "current": 3401.881,
            "min": 1500.0,
            "max": 2250.0
        },
        {
            "current": 3386.501,
            "min": 1500.0,
            "max": 2250.0
        },
        {
            "current": 3380.129,
            "min": 1500.0,
            "max": 2250.0
        },
        {
            "current": 2572.62,
            "min": 1500.0,
            "max": 2250.0
        },
        {
            "current": 3393.173,
            "min": 1500.0,
            "max": 2250.0
        },
        {
            "current": 3391.063,
            "min": 1500.0,
            "max": 2250.0
        },
        {
            "current": 3396.031,
            "min": 1500.0,
            "max": 2250.0
        },
        {
            "current": 3380.91,
            "min": 1500.0,
            "max": 2250.0
        },
        {
            "current": 3401.726,
            "min": 1500.0,
            "max": 2250.0
        },
        {
            "current": 2306.182,
            "min": 1500.0,
            "max": 2250.0
        },
        {
            "current": 3383.2,
            "min": 1500.0,
            "max": 2250.0
        },
        {
            "current": 3397.87,
            "min": 1500.0,
            "max": 2250.0
        },
        {
            "current": 3385.712,
            "min": 1500.0,
            "max": 2250.0
        },
        {
            "current": 3388.211,
            "min": 1500.0,
            "max": 2250.0
        },
        {
            "current": 3393.068,
            "min": 1500.0,
            "max": 2250.0
        },
        {
            "current": 3393.695,
            "min": 1500.0,
            "max": 2250.0
        },
        {
            "current": 3391.961,
            "min": 1500.0,
            "max": 2250.0
        },
        {
            "current": 3392.636,
            "min": 1500.0,
            "max": 2250.0
        },
        {
            "current": 3392.058,
            "min": 1500.0,
            "max": 2250.0
        },
        {
            "current": 3387.966,
            "min": 1500.0,
            "max": 2250.0
        },
        {
            "current": 3392.867,
            "min": 1500.0,
            "max": 2250.0
        },
        {
            "current": 3388.081,
            "min": 1500.0,
            "max": 2250.0
        },
        {
            "current": 3389.457,
            "min": 1500.0,
            "max": 2250.0
        },
        {
            "current": 3277.354,
            "min": 1500.0,
            "max": 2250.0
        },
        {
            "current": 2258.268,
            "min": 1500.0,
            "max": 2250.0
        },
        {
            "current": 3378.289,
            "min": 1500.0,
            "max": 2250.0
        },
        {
            "current": 3393.619,
            "min": 1500.0,
            "max": 2250.0
        },
        {
            "current": 2510.347,
            "min": 1500.0,
            "max": 2250.0
        },
        {
            "current": 2479.833,
            "min": 1500.0,
            "max": 2250.0
        },
        {
            "current": 3380.529,
            "min": 1500.0,
            "max": 2250.0
        },
        {
            "current": 3378.65,
            "min": 1500.0,
            "max": 2250.0
        },
        {
            "current": 3381.004,
            "min": 1500.0,
            "max": 2250.0
        },
        {
            "current": 2422.012,
            "min": 1500.0,
            "max": 2250.0
        },
        {
            "current": 2330.701,
            "min": 1500.0,
            "max": 2250.0
        },
        {
            "current": 3392.954,
            "min": 1500.0,
            "max": 2250.0
        },
        {
            "current": 3393.059,
            "min": 1500.0,
            "max": 2250.0
        },
        {
            "current": 3393.942,
            "min": 1500.0,
            "max": 2250.0
        },
        {
            "current": 3398.537,
            "min": 1500.0,
            "max": 2250.0
        },
        {
            "current": 3350.836,
            "min": 1500.0,
            "max": 2250.0
        },
        {
            "current": 3385.644,
            "min": 1500.0,
            "max": 2250.0
        },
        {
            "current": 2532.671,
            "min": 1500.0,
            "max": 2250.0
        },
        {
            "current": 3393.01,
            "min": 1500.0,
            "max": 2250.0
        },
        {
            "current": 3383.232,
            "min": 1500.0,
            "max": 2250.0
        },
        {
            "current": 3375.563,
            "min": 1500.0,
            "max": 2250.0
        },
        {
            "current": 2887.312,
            "min": 1500.0,
            "max": 2250.0
        },
        {
            "current": 3393.185,
            "min": 1500.0,
            "max": 2250.0
        },
        {
            "current": 3393.316,
            "min": 1500.0,
            "max": 2250.0
        },
        {
            "current": 3384.102,
            "min": 1500.0,
            "max": 2250.0
        },
        {
            "current": 3391.544,
            "min": 1500.0,
            "max": 2250.0
        },
        {
            "current": 3401.548,
            "min": 1500.0,
            "max": 2250.0
        },
        {
            "current": 3383.334,
            "min": 1500.0,
            "max": 2250.0
        },
        {
            "current": 2248.511,
            "min": 1500.0,
            "max": 2250.0
        },
        {
            "current": 3396.65,
            "min": 1500.0,
            "max": 2250.0
        },
        {
            "current": 2345.766,
            "min": 1500.0,
            "max": 2250.0
        },
        {
            "current": 2319.608,
            "min": 1500.0,
            "max": 2250.0
        },
        {
            "current": 3390.858,
            "min": 1500.0,
            "max": 2250.0
        },
        {
            "current": 1729.068,
            "min": 1500.0,
            "max": 2250.0
        },
        {
            "current": 3396.15,
            "min": 1500.0,
            "max": 2250.0
        },
        {
            "current": 3395.757,
            "min": 1500.0,
            "max": 2250.0
        },
        {
            "current": 3386.672,
            "min": 1500.0,
            "max": 2250.0
        },
        {
            "current": 2253.638,
            "min": 1500.0,
            "max": 2250.0
        },
        {
            "current": 3389.834,
            "min": 1500.0,
            "max": 2250.0
        },
        {
            "current": 3389.181,
            "min": 1500.0,
            "max": 2250.0
        },
        {
            "current": 3391.612,
            "min": 1500.0,
            "max": 2250.0
        },
        {
            "current": 2251.943,
            "min": 1500.0,
            "max": 2250.0
        },
        {
            "current": 2905.459,
            "min": 1500.0,
            "max": 2250.0
        },
        {
            "current": 2242.962,
            "min": 1500.0,
            "max": 2250.0
        },
        {
            "current": 2265.924,
            "min": 1500.0,
            "max": 2250.0
        },
        {
            "current": 3393.895,
            "min": 1500.0,
            "max": 2250.0
        },
        {
            "current": 3383.198,
            "min": 1500.0,
            "max": 2250.0
        },
        {
            "current": 3388.828,
            "min": 1500.0,
            "max": 2250.0
        },
        {
            "current": 3384.746,
            "min": 1500.0,
            "max": 2250.0
        },
        {
            "current": 2266.755,
            "min": 1500.0,
            "max": 2250.0
        },
        {
            "current": 3386.987,
            "min": 1500.0,
            "max": 2250.0
        },
        {
            "current": 3384.239,
            "min": 1500.0,
            "max": 2250.0
        },
        {
            "current": 3393.987,
            "min": 1500.0,
            "max": 2250.0
        },
        {
            "current": 3392.257,
            "min": 1500.0,
            "max": 2250.0
        },
        {
            "current": 3392.344,
            "min": 1500.0,
            "max": 2250.0
        },
        {
            "current": 3392.708,
            "min": 1500.0,
            "max": 2250.0
        },
        {
            "current": 3393.617,
            "min": 1500.0,
            "max": 2250.0
        },
        {
            "current": 3394.162,
            "min": 1500.0,
            "max": 2250.0
        },
        {
            "current": 3395.698,
            "min": 1500.0,
            "max": 2250.0
        },
        {
            "current": 3389.087,
            "min": 1500.0,
            "max": 2250.0
        },
        {
            "current": 3386.935,
            "min": 1500.0,
            "max": 2250.0
        },
        {
            "current": 3399.854,
            "min": 1500.0,
            "max": 2250.0
        },
        {
            "current": 2539.074,
            "min": 1500.0,
            "max": 2250.0
        },
        {
            "current": 3383.466,
            "min": 1500.0,
            "max": 2250.0
        },
        {
            "current": 3397.753,
            "min": 1500.0,
            "max": 2250.0
        },
        {
            "current": 3379.828,
            "min": 1500.0,
            "max": 2250.0
        },
        {
            "current": 3387.149,
            "min": 1500.0,
            "max": 2250.0
        },
        {
            "current": 3382.465,
            "min": 1500.0,
            "max": 2250.0
        },
        {
            "current": 3405.189,
            "min": 1500.0,
            "max": 2250.0
        },
        {
            "current": 2240.84,
            "min": 1500.0,
            "max": 2250.0
        },
        {
            "current": 3381.886,
            "min": 1500.0,
            "max": 2250.0
        },
        {
            "current": 3393.827,
            "min": 1500.0,
            "max": 2250.0
        },
        {
            "current": 3392.48,
            "min": 1500.0,
            "max": 2250.0
        },
        {
            "current": 3390.464,
            "min": 1500.0,
            "max": 2250.0
        },
        {
            "current": 3385.867,
            "min": 1500.0,
            "max": 2250.0
        },
        {
            "current": 3393.396,
            "min": 1500.0,
            "max": 2250.0
        },
        {
            "current": 3384.817,
            "min": 1500.0,
            "max": 2250.0
        },
        {
            "current": 2227.281,
            "min": 1500.0,
            "max": 2250.0
        },
        {
            "current": 3398.922,
            "min": 1500.0,
            "max": 2250.0
        },
        {
            "current": 3389.973,
            "min": 1500.0,
            "max": 2250.0
        },
        {
            "current": 3393.65,
            "min": 1500.0,
            "max": 2250.0
        },
        {
            "current": 3393.734,
            "min": 1500.0,
            "max": 2250.0
        },
        {
            "current": 3384.519,
            "min": 1500.0,
            "max": 2250.0
        },
        {
            "current": 3332.909,
            "min": 1500.0,
            "max": 2250.0
        },
        {
            "current": 3391.669,
            "min": 1500.0,
            "max": 2250.0
        },
        {
            "current": 2207.997,
            "min": 1500.0,
            "max": 2250.0
        },
        {
            "current": 3382.284,
            "min": 1500.0,
            "max": 2250.0
        },
        {
            "current": 3393.746,
            "min": 1500.0,
            "max": 2250.0
        },
        {
            "current": 3393.591,
            "min": 1500.0,
            "max": 2250.0
        },
        {
            "current": 3379.094,
            "min": 1500.0,
            "max": 2250.0
        },
        {
            "current": 3387.973,
            "min": 1500.0,
            "max": 2250.0
        },
        {
            "current": 3393.026,
            "min": 1500.0,
            "max": 2250.0
        },
        {
            "current": 3393.889,
            "min": 1500.0,
            "max": 2250.0
        },
        {
            "current": 3389.035,
            "min": 1500.0,
            "max": 2250.0
        },
        {
            "current": 3384.869,
            "min": 1500.0,
            "max": 2250.0
        },
        {
            "current": 3388.073,
            "min": 1500.0,
            "max": 2250.0
        },
        {
            "current": 3392.24,
            "min": 1500.0,
            "max": 2250.0
        },
        {
            "current": 2547.472,
            "min": 1500.0,
            "max": 2250.0
        },
        {
            "current": 2453.193,
            "min": 1500.0,
            "max": 2250.0
        },
        {
            "current": 2265.17,
            "min": 1500.0,
            "max": 2250.0
        },
        {
            "current": 3379.893,
            "min": 1500.0,
            "max": 2250.0
        },
        {
            "current": 3331.604,
            "min": 1500.0,
            "max": 2250.0
        },
        {
            "current": 3396.091,
            "min": 1500.0,
            "max": 2250.0
        },
        {
            "current": 3359.333,
            "min": 1500.0,
            "max": 2250.0
        },
        {
            "current": 3382.297,
            "min": 1500.0,
            "max": 2250.0
        },
        {
            "current": 3387.629,
            "min": 1500.0,
            "max": 2250.0
        },
        {
            "current": 3388.641,
            "min": 1500.0,
            "max": 2250.0
        },
        {
            "current": 3378.8,
            "min": 1500.0,
            "max": 2250.0
        },
        {
            "current": 2579.961,
            "min": 1500.0,
            "max": 2250.0
        },
        {
            "current": 3385.162,
            "min": 1500.0,
            "max": 2250.0
        },
        {
            "current": 3390.579,
            "min": 1500.0,
            "max": 2250.0
        },
        {
            "current": 3378.672,
            "min": 1500.0,
            "max": 2250.0
        },
        {
            "current": 3391.42,
            "min": 1500.0,
            "max": 2250.0
        },
        {
            "current": 3395.504,
            "min": 1500.0,
            "max": 2250.0
        },
        {
            "current": 2358.022,
            "min": 1500.0,
            "max": 2250.0
        },
        {
            "current": 3388.946,
            "min": 1500.0,
            "max": 2250.0
        },
        {
            "current": 3396.758,
            "min": 1500.0,
            "max": 2250.0
        },
        {
            "current": 3379.576,
            "min": 1500.0,
            "max": 2250.0
        },
        {
            "current": 3391.206,
            "min": 1500.0,
            "max": 2250.0
        },
        {
            "current": 3379.126,
            "min": 1500.0,
            "max": 2250.0
        },
        {
            "current": 3393.317,
            "min": 1500.0,
            "max": 2250.0
        },
        {
            "current": 3390.765,
            "min": 1500.0,
            "max": 2250.0
        },
        {
            "current": 3392.714,
            "min": 1500.0,
            "max": 2250.0
        },
        {
            "current": 3378.53,
            "min": 1500.0,
            "max": 2250.0
        },
        {
            "current": 3400.579,
            "min": 1500.0,
            "max": 2250.0
        },
        {
            "current": 3392.81,
            "min": 1500.0,
            "max": 2250.0
        },
        {
            "current": 3380.011,
            "min": 1500.0,
            "max": 2250.0
        },
        {
            "current": 3399.019,
            "min": 1500.0,
            "max": 2250.0
        },
        {
            "current": 3394.307,
            "min": 1500.0,
            "max": 2250.0
        },
        {
            "current": 3169.448,
            "min": 1500.0,
            "max": 2250.0
        },
        {
            "current": 2500.799,
            "min": 1500.0,
            "max": 2250.0
        },
        {
            "current": 3394.733,
            "min": 1500.0,
            "max": 2250.0
        },
        {
            "current": 3310.237,
            "min": 1500.0,
            "max": 2250.0
        },
        {
            "current": 2508.843,
            "min": 1500.0,
            "max": 2250.0
        },
        {
            "current": 3384.911,
            "min": 1500.0,
            "max": 2250.0
        },
        {
            "current": 3393.291,
            "min": 1500.0,
            "max": 2250.0
        },
        {
            "current": 2014.194,
            "min": 1500.0,
            "max": 2250.0
        },
        {
            "current": 3318.107,
            "min": 1500.0,
            "max": 2250.0
        },
        {
            "current": 2328.755,
            "min": 1500.0,
            "max": 2250.0
        },
        {
            "current": 3392.41,
            "min": 1500.0,
            "max": 2250.0
        },
        {
            "current": 3384.05,
            "min": 1500.0,
            "max": 2250.0
        },
        {
            "current": 3388.049,
            "min": 1500.0,
            "max": 2250.0
        },
        {
            "current": 3393.309,
            "min": 1500.0,
            "max": 2250.0
        },
        {
            "current": 2511.149,
            "min": 1500.0,
            "max": 2250.0
        },
        {
            "current": 3383.583,
            "min": 1500.0,
            "max": 2250.0
        },
        {
            "current": 2501.13,
            "min": 1500.0,
            "max": 2250.0
        },
        {
            "current": 3385.576,
            "min": 1500.0,
            "max": 2250.0
        },
        {
            "current": 3390.775,
            "min": 1500.0,
            "max": 2250.0
        },
        {
            "current": 3389.323,
            "min": 1500.0,
            "max": 2250.0
        },
        {
            "current": 2532.761,
            "min": 1500.0,
            "max": 2250.0
        },
        {
            "current": 3393.499,
            "min": 1500.0,
            "max": 2250.0
        },
        {
            "current": 3379.347,
            "min": 1500.0,
            "max": 2250.0
        },
        {
            "current": 3372.474,
            "min": 1500.0,
            "max": 2250.0
        },
        {
            "current": 3401.845,
            "min": 1500.0,
            "max": 2250.0
        },
        {
            "current": 3391.754,
            "min": 1500.0,
            "max": 2250.0
        },
        {
            "current": 3390.684,
            "min": 1500.0,
            "max": 2250.0
        },
        {
            "current": 2282.318,
            "min": 1500.0,
            "max": 2250.0
        },
        {
            "current": 3393.088,
            "min": 1500.0,
            "max": 2250.0
        },
        {
            "current": 2351.767,
            "min": 1500.0,
            "max": 2250.0
        },
        {
            "current": 2168.752,
            "min": 1500.0,
            "max": 2250.0
        },
        {
            "current": 3397.123,
            "min": 1500.0,
            "max": 2250.0
        },
        {
            "current": 1905.15,
            "min": 1500.0,
            "max": 2250.0
        },
        {
            "current": 3383.931,
            "min": 1500.0,
            "max": 2250.0
        },
        {
            "current": 3390.915,
            "min": 1500.0,
            "max": 2250.0
        },
        {
            "current": 3395.396,
            "min": 1500.0,
            "max": 2250.0
        },
        {
            "current": 2287.734,
            "min": 1500.0,
            "max": 2250.0
        },
        {
            "current": 3387.7,
            "min": 1500.0,
            "max": 2250.0
        },
        {
            "current": 3396.543,
            "min": 1500.0,
            "max": 2250.0
        },
        {
            "current": 3385.639,
            "min": 1500.0,
            "max": 2250.0
        },
        {
            "current": 3247.679,
            "min": 1500.0,
            "max": 2250.0
        },
        {
            "current": 3396.426,
            "min": 1500.0,
            "max": 2250.0
        },
        {
            "current": 2275.906,
            "min": 1500.0,
            "max": 2250.0
        },
        {
            "current": 2281.132,
            "min": 1500.0,
            "max": 2250.0
        },
        {
            "current": 3395.883,
            "min": 1500.0,
            "max": 2250.0
        },
        {
            "current": 3379.915,
            "min": 1500.0,
            "max": 2250.0
        },
        {
            "current": 3393.508,
            "min": 1500.0,
            "max": 2250.0
        },
        {
            "current": 3386.332,
            "min": 1500.0,
            "max": 2250.0
        },
        {
            "current": 2283.005,
            "min": 1500.0,
            "max": 2250.0
        },
        {
            "current": 3391.74,
            "min": 1500.0,
            "max": 2250.0
        },
        {
            "current": 3393.181,
            "min": 1500.0,
            "max": 2250.0
        },
        {
            "current": 3392.331,
            "min": 1500.0,
            "max": 2250.0
        },
        {
            "current": 3393.001,
            "min": 1500.0,
            "max": 2250.0
        },
        {
            "current": 3396.558,
            "min": 1500.0,
            "max": 2250.0
        },
        {
            "current": 3393.549,
            "min": 1500.0,
            "max": 2250.0
        },
        {
            "current": 3380.904,
            "min": 1500.0,
            "max": 2250.0
        },
        {
            "current": 3393.877,
            "min": 1500.0,
            "max": 2250.0
        },
        {
            "current": 3393.576,
            "min": 1500.0,
            "max": 2250.0
        },
        {
            "current": 3403.367,
            "min": 1500.0,
            "max": 2250.0
        },
        {
            "current": 3393.246,
            "min": 1500.0,
            "max": 2250.0
        },
        {
            "current": 3376.738,
            "min": 1500.0,
            "max": 2250.0
        },
        {
            "current": 2439.316,
            "min": 1500.0,
            "max": 2250.0
        },
        {
            "current": 3389.065,
            "min": 1500.0,
            "max": 2250.0
        },
        {
            "current": 3390.213,
            "min": 1500.0,
            "max": 2250.0
        },
        {
            "current": 3392.86,
            "min": 1500.0,
            "max": 2250.0
        },
        {
            "current": 3393.85,
            "min": 1500.0,
            "max": 2250.0
        },
        {
            "current": 3398.071,
            "min": 1500.0,
            "max": 2250.0
        },
        {
            "current": 3398.725,
            "min": 1500.0,
            "max": 2250.0
        },
        {
            "current": 2260.785,
            "min": 1500.0,
            "max": 2250.0
        },
        {
            "current": 3384.064,
            "min": 1500.0,
            "max": 2250.0
        },
        {
            "current": 3404.901,
            "min": 1500.0,
            "max": 2250.0
        },
        {
            "current": 3391.608,
            "min": 1500.0,
            "max": 2250.0
        },
        {
            "current": 3390.6,
            "min": 1500.0,
            "max": 2250.0
        },
        {
            "current": 3396.416,
            "min": 1500.0,
            "max": 2250.0
        },
        {
            "current": 3389.822,
            "min": 1500.0,
            "max": 2250.0
        },
        {
            "current": 3402.327,
            "min": 1500.0,
            "max": 2250.0
        },
        {
            "current": 2385.034,
            "min": 1500.0,
            "max": 2250.0
        },
        {
            "current": 3388.075,
            "min": 1500.0,
            "max": 2250.0
        },
        {
            "current": 3392.774,
            "min": 1500.0,
            "max": 2250.0
        },
        {
            "current": 3393.603,
            "min": 1500.0,
            "max": 2250.0
        },
        {
            "current": 3394.192,
            "min": 1500.0,
            "max": 2250.0
        },
        {
            "current": 3358.041,
            "min": 1500.0,
            "max": 2250.0
        },
        {
            "current": 3304.2,
            "min": 1500.0,
            "max": 2250.0
        },
        {
            "current": 2193.077,
            "min": 1500.0,
            "max": 2250.0
        },
        {
            "current": 3384.612,
            "min": 1500.0,
            "max": 2250.0
        },
        {
            "current": 3392.015,
            "min": 1500.0,
            "max": 2250.0
        },
        {
            "current": 3384.623,
            "min": 1500.0,
            "max": 2250.0
        },
        {
            "current": 3392.505,
            "min": 1500.0,
            "max": 2250.0
        },
        {
            "current": 3386.059,
            "min": 1500.0,
            "max": 2250.0
        }
    ],
    "disk": {
        "/": {
            "total": 1757.7545127868652,
            "used": 1279.7060317993164
        }
    },
    "gpu": "NVIDIA A100-SXM4-80GB",
    "gpu_count": 8,
    "gpu_devices": [
        {
            "name": "NVIDIA A100-SXM4-80GB",
            "memory_total": 85899345920
        },
        {
            "name": "NVIDIA A100-SXM4-80GB",
            "memory_total": 85899345920
        },
        {
            "name": "NVIDIA A100-SXM4-80GB",
            "memory_total": 85899345920
        },
        {
            "name": "NVIDIA A100-SXM4-80GB",
            "memory_total": 85899345920
        },
        {
            "name": "NVIDIA A100-SXM4-80GB",
            "memory_total": 85899345920
        },
        {
            "name": "NVIDIA A100-SXM4-80GB",
            "memory_total": 85899345920
        },
        {
            "name": "NVIDIA A100-SXM4-80GB",
            "memory_total": 85899345920
        },
        {
            "name": "NVIDIA A100-SXM4-80GB",
            "memory_total": 85899345920
        }
    ],
    "memory": {
        "total": 2015.6736488342285
    }
}
